Pywrt/Pywrt.py
Pywrt/__init__.py
Pywrt-1.3.dist-info/LICENSE
Pywrt-1.3.dist-info/METADATA
Pywrt-1.3.dist-info/WHEEL
Pywrt-1.3.dist-info/top_level.txt
Pywrt-1.3.dist-info/RECORD
