Metadata-Version: 2.1
Name: Pywrt
Version: 1.3
Summary: Pacote para traduzir textos e documentos
Author: Welison Andrade
Author-email: 
Classifier: Programming Language :: Python :: 3
Classifier: License :: OSI Approved :: MIT License
Requires-Python: >=3.6
License-File: LICENSE
